LICENSE
MANIFEST.in
README.md
pyproject.toml
setup.py
SDL2/SDL.h
SDL2/SDL_assert.h
SDL2/SDL_atomic.h
SDL2/SDL_audio.h
SDL2/SDL_bits.h
SDL2/SDL_blendmode.h
SDL2/SDL_clipboard.h
SDL2/SDL_config.h
SDL2/SDL_cpuinfo.h
SDL2/SDL_egl.h
SDL2/SDL_endian.h
SDL2/SDL_error.h
SDL2/SDL_events.h
SDL2/SDL_filesystem.h
SDL2/SDL_gamecontroller.h
SDL2/SDL_gesture.h
SDL2/SDL_haptic.h
SDL2/SDL_hints.h
SDL2/SDL_joystick.h
SDL2/SDL_keyboard.h
SDL2/SDL_keycode.h
SDL2/SDL_loadso.h
SDL2/SDL_log.h
SDL2/SDL_main.h
SDL2/SDL_messagebox.h
SDL2/SDL_mouse.h
SDL2/SDL_mutex.h
SDL2/SDL_name.h
SDL2/SDL_opengl.h
SDL2/SDL_opengl_glext.h
SDL2/SDL_opengles.h
SDL2/SDL_opengles2.h
SDL2/SDL_opengles2_gl2.h
SDL2/SDL_opengles2_gl2ext.h
SDL2/SDL_opengles2_gl2platform.h
SDL2/SDL_opengles2_khrplatform.h
SDL2/SDL_pixels.h
SDL2/SDL_platform.h
SDL2/SDL_power.h
SDL2/SDL_quit.h
SDL2/SDL_rect.h
SDL2/SDL_render.h
SDL2/SDL_revision.h
SDL2/SDL_rwops.h
SDL2/SDL_scancode.h
SDL2/SDL_sensor.h
SDL2/SDL_shape.h
SDL2/SDL_stdinc.h
SDL2/SDL_surface.h
SDL2/SDL_system.h
SDL2/SDL_syswm.h
SDL2/SDL_test.h
SDL2/SDL_test_assert.h
SDL2/SDL_test_common.h
SDL2/SDL_test_compare.h
SDL2/SDL_test_crc32.h
SDL2/SDL_test_font.h
SDL2/SDL_test_fuzzer.h
SDL2/SDL_test_harness.h
SDL2/SDL_test_images.h
SDL2/SDL_test_log.h
SDL2/SDL_test_md5.h
SDL2/SDL_test_memory.h
SDL2/SDL_test_random.h
SDL2/SDL_thread.h
SDL2/SDL_timer.h
SDL2/SDL_touch.h
SDL2/SDL_ttf.h
SDL2/SDL_types.h
SDL2/SDL_version.h
SDL2/SDL_video.h
SDL2/SDL_vulkan.h
SDL2/_real_SDL_config.h
SDL2/begin_code.h
SDL2/close_code.h
lib/libSDL2-2.0.so
lib/libSDL2_image-2.0.so
lib/libSDL2_ttf-2.0.so
mojave_eda/__init__.py
mojave_eda/_mojave.c
mojave_eda/mojave_eda.py
mojave_eda.egg-info/PKG-INFO
mojave_eda.egg-info/SOURCES.txt
mojave_eda.egg-info/dependency_links.txt
mojave_eda.egg-info/top_level.txt
mojave_eda/font/DejaVuSans.ttf
mojave_eda/font/License.html
mojave_eda/images/README
mojave_eda/images/example_bash.gif
mojave_eda/images/example_mojave.png
mojave_eda/images/example_toy.gif
mojave_eda/images/mojave_cut.bmp
mojave_eda/images/mojave_erase.bmp
mojave_eda/images/mojave_intensity.bmp
mojave_eda/images/mojave_logo.bmp
