Metadata-Version: 2.1
Name: mojave_eda
Version: 0.0.6
Summary: Multidimensional data visualization
Author-email: Kevin Player <kjplaye@gmail.com>
Project-URL: Homepage, https://github.com/kjplaye/mojave
Classifier: Programming Language :: Python :: 3
Classifier: License :: OSI Approved :: MIT License
Classifier: Operating System :: OS Independent
Requires-Python: >=3.0
License-File: LICENSE
